podload/__init__.py
podload/exceptions.py
podload/manager.py
podload/podcast.py
podload-1.5.1.dist-info/LICENSE
podload-1.5.1.dist-info/METADATA
podload-1.5.1.dist-info/WHEEL
podload-1.5.1.dist-info/entry_points.txt
podload-1.5.1.dist-info/top_level.txt
podload-1.5.1.dist-info/RECORD
